Metadata-Version: 1.1
Name: soft-django-delete
Version: 0.0.2
Summary: Django Soft Deletion Package
Home-page: https://github.com/yucealiosman/soft-delete/
Author: Ali Osman Yuce
Author-email: aliosmanyuce@gmail.com
License: MIT
Platform: UNKNOWN
Classifier: Programming Language :: Python
Classifier: Programming Language :: Python :: 3.6
